multi_ai/__init__.py
multi_ai/models.py
multi_ai/utils.py
multimodel_ai-0.1.6.dist-info/licenses/LICENSE
multimodel_ai-0.1.6.dist-info/METADATA
multimodel_ai-0.1.6.dist-info/WHEEL
multimodel_ai-0.1.6.dist-info/entry_points.txt
multimodel_ai-0.1.6.dist-info/top_level.txt
multimodel_ai-0.1.6.dist-info/RECORD
