Metadata-Version: 2.4
Name: multimodel-ai
Version: 0.1.6
Summary: A Python module for efficient multi-model AI inference with memory management
Author-email: VRImage <vrimage70@gmail.com>
License-Expression: MIT
Project-URL: Homepage, https://github.com/VRImage/multimodel-ai
Classifier: Programming Language :: Python :: 3
Classifier: Operating System :: OS Independent
Classifier: Development Status :: 4 - Beta
Classifier: Intended Audience :: Developers
Classifier: Topic :: Software Development :: Libraries :: Python Modules
Requires-Python: >=3.8
License-File: LICENSE
Requires-Dist: accelerate>=1.6.0
Requires-Dist: qwen-omni-utils[decord]>=0.0.4
Requires-Dist: qwen-vl-utils[decord]==0.0.8
Requires-Dist: torchvision>=0.21.0
Requires-Dist: bitsandbytes>=0.45.5
Requires-Dist: transformers>=4.37.0
Requires-Dist: torch>=2.6.0
Requires-Dist: torchaudio>=2.6.0
Requires-Dist: librosa>=0.11.0
Requires-Dist: soundfile>=0.13.1
Requires-Dist: numpy>=1.22.3
Requires-Dist: scipy>=1.6.0
Dynamic: license-file
